Hive/__init__.py
Hive/configs/ATM_nnUNet_3D_fullres_config.json
Hive/configs/AutoPET_Positive_nnDet_3D_fullres_config.json
Hive/configs/LungLobeSeg_nnUNet_3D_fullres_In_config.json
Hive/configs/LymphNodeSeg_ABD_nnDet_3D_fullres_config.json
Hive/configs/LymphNodeSeg_MED_nnDet_3D_fullres_config.json
Hive/configs/__init__.py
Hive/configs/nnDet_config_template.json
Hive/evaluation/__init__.py
Hive/evaluation/abstract.py
Hive/evaluation/detection/__init__.py
Hive/evaluation/detection/coco.py
Hive/evaluation/detection/froc.py
Hive/evaluation/detection/hist.py
Hive/evaluation/detection/matching.py
Hive/utils/__init__.py
Hive/utils/file_utils.py
Hive/utils/log_utils.py
Hive/utils/seg_mask_utils.py
Hive/utils/volume_utils.py
Hive_scripts/Hive_convert_DICOM_dataset_to_NIFTI_dataset.py
Hive_scripts/Hive_convert_NIFTI_predictions_to_DICOM_SEG.py
Hive_scripts/Hive_convert_semantic_to_instance_segmentation.py
Hive_scripts/Hive_create_subset.py
Hive_scripts/Hive_extract_experiment_predictions.py
Hive_scripts/Hive_order_data_folder.py
Hive_scripts/Hive_run_pipeline_from_file.py
Hive_scripts/__init__.py
Hive_scripts/nndet_compute_metric_results.py
Hive_scripts/nndet_create_pipeline.py
Hive_scripts/nndet_prepare_data_folder.py
Hive_scripts/nndet_run_preprocessing.py
Hive_scripts/nndet_run_training.py
Hive_scripts/nnunet_prepare_data_folder.py
Hive_scripts/nnunet_run_prediction.py
Hive_scripts/nnunet_run_preprocessing.py
Hive_scripts/nnunet_run_training.py
Hive_scripts/script_template.py
Hive_scripts/upload_DICOM_to_Orthanc.py
hive_maia-1.1.1.data/data/VERSION
hive_maia-1.1.1.data/data/requirements.txt
hive_maia-1.1.1.dist-info/LICENSE
hive_maia-1.1.1.dist-info/METADATA
hive_maia-1.1.1.dist-info/WHEEL
hive_maia-1.1.1.dist-info/entry_points.txt
hive_maia-1.1.1.dist-info/top_level.txt
hive_maia-1.1.1.dist-info/RECORD
