Metadata-Version: 2.1
Name: hive-maia
Version: 1.1.1
Summary: Python Package to support Deep Learning data preparation, pre-processing. training, result visualization and model deployment across different frameworks (nnUNet, nnDetection, MONAI).
Home-page: https://github.com/MAIA-KTH/Hive.git
Author: Simone Bendazzoli
Author-email: simben@kth.se
License: GPLv3
Project-URL: Documentation, https://hive-maia.readthedocs.io
Project-URL: Source, https://github.com/MAIA-KTH/Hive
Project-URL: Tracker, https://github.com/MAIA-KTH/Hive/issues
Keywords: deep learning,image segmentation,medical image analysis,medical image segmentation,object detection
Platform: UNKNOWN
License-File: LICENSE
Requires-Dist: coloredlogs
Requires-Dist: dicom2nifti
Requires-Dist: loguru
Requires-Dist: matplotlib
Requires-Dist: nibabel
Requires-Dist: numpy
Requires-Dist: pydicom
Requires-Dist: pydicom-seg
Requires-Dist: pynvml
Requires-Dist: scikit-learn
Requires-Dist: scipy
Requires-Dist: SimpleITK
Requires-Dist: tqdm
Requires-Dist: pandas
Requires-Dist: openpyxl
